redpepper/tools/__init__.py
redpepper/tools/entrypoint.py
redpepper/tools/install_redpepper_console.py
redpepper/tools/install_step_binaries.py
redpepper/tools/login_management.py
redpepper/tools/setup_step_ca.py
redpepper/tools/step_ca_keypair.py
redpepper_tools-0.3.3.dist-info/METADATA
redpepper_tools-0.3.3.dist-info/WHEEL
redpepper_tools-0.3.3.dist-info/entry_points.txt
redpepper_tools-0.3.3.dist-info/RECORD
