Metadata-Version: 2.4
Name: redpepper-tools
Version: 0.3.3
Summary: A state-based server management system (related tools package)
License: MIT License
Classifier: Development Status :: 3 - Alpha
Classifier: Intended Audience :: Developers
Classifier: Intended Audience :: Information Technology
Classifier: License :: OSI Approved :: MIT License
Classifier: Operating System :: POSIX :: Linux
Classifier: Programming Language :: Python :: 3
Classifier: Topic :: System :: Installation/Setup
Classifier: Topic :: System :: Systems Administration
Requires-Python: >=3.12
Requires-Dist: argon2-cffi>=23.1.0
Requires-Dist: pyotp>=2.9.0
Requires-Dist: qrcode>=8.0
Requires-Dist: requests>=2.32.3
Requires-Dist: typer>=0.12.5
